MANIFEST.in
setup.py
QEnvPython38.egg-info/PKG-INFO
QEnvPython38.egg-info/SOURCES.txt
QEnvPython38.egg-info/dependency_links.txt
QEnvPython38.egg-info/top_level.txt
QPT_SDK/__init__.py
QPT_SDK/QEnvPython/__init__.py
QPT_SDK/QEnvPython/python38/LICENSE.txt
QPT_SDK/QEnvPython/python38/_asyncio.pyd
QPT_SDK/QEnvPython/python38/_bz2.pyd
QPT_SDK/QEnvPython/python38/_ctypes.pyd
QPT_SDK/QEnvPython/python38/_decimal.pyd
QPT_SDK/QEnvPython/python38/_elementtree.pyd
QPT_SDK/QEnvPython/python38/_hashlib.pyd
QPT_SDK/QEnvPython/python38/_lzma.pyd
QPT_SDK/QEnvPython/python38/_msi.pyd
QPT_SDK/QEnvPython/python38/_multiprocessing.pyd
QPT_SDK/QEnvPython/python38/_overlapped.pyd
QPT_SDK/QEnvPython/python38/_queue.pyd
QPT_SDK/QEnvPython/python38/_socket.pyd
QPT_SDK/QEnvPython/python38/_sqlite3.pyd
QPT_SDK/QEnvPython/python38/_ssl.pyd
QPT_SDK/QEnvPython/python38/libcrypto-1_1.dll
QPT_SDK/QEnvPython/python38/libffi-7.dll
QPT_SDK/QEnvPython/python38/libssl-1_1.dll
QPT_SDK/QEnvPython/python38/pyexpat.pyd
QPT_SDK/QEnvPython/python38/python.cat
QPT_SDK/QEnvPython/python38/python.exe
QPT_SDK/QEnvPython/python38/python3.dll
QPT_SDK/QEnvPython/python38/python38._pth
QPT_SDK/QEnvPython/python38/python38.dll
QPT_SDK/QEnvPython/python38/python38.zip
QPT_SDK/QEnvPython/python38/pythonw.exe
QPT_SDK/QEnvPython/python38/select.pyd
QPT_SDK/QEnvPython/python38/sqlite3.dll
QPT_SDK/QEnvPython/python38/unicodedata.pyd
QPT_SDK/QEnvPython/python38/vcruntime140.dll
QPT_SDK/QEnvPython/python38/vcruntime140_1.dll
QPT_SDK/QEnvPython/python38/winsound.pyd
QPT_SDK/QEnvPython/python38/Lib/site-packages/distutils-precedence.pth
QPT_SDK/QEnvPython/python38/Lib/site-packages/_distutils_hack/__init__.py
QPT_SDK/QEnvPython/python38/Lib/site-packages/_distutils_hack/override.py
QPT_SDK/QEnvPython/python38/Lib/site-packages/pip/__init__.py
QPT_SDK/QEnvPython/python38/Lib/site-packages/pip/__main__.py
QPT_SDK/QEnvPython/python38/Lib/site-packages/pip/__pip-runner__.py
QPT_SDK/QEnvPython/python38/Lib/site-packages/pip/py.typed
QPT_SDK/QEnvPython/python38/Lib/site-packages/pip-23.3.1.dist-info/AUTHORS.txt
QPT_SDK/QEnvPython/python38/Lib/site-packages/pip-23.3.1.dist-info/INSTALLER
QPT_SDK/QEnvPython/python38/Lib/site-packages/pip-23.3.1.dist-info/LICENSE.txt
QPT_SDK/QEnvPython/python38/Lib/site-packages/pip-23.3.1.dist-info/METADATA
QPT_SDK/QEnvPython/python38/Lib/site-packages/pip-23.3.1.dist-info/RECORD
QPT_SDK/QEnvPython/python38/Lib/site-packages/pip-23.3.1.dist-info/REQUESTED
QPT_SDK/QEnvPython/python38/Lib/site-packages/pip-23.3.1.dist-info/WHEEL
QPT_SDK/QEnvPython/python38/Lib/site-packages/pip-23.3.1.dist-info/entry_points.txt
QPT_SDK/QEnvPython/python38/Lib/site-packages/pip-23.3.1.dist-info/top_level.txt
QPT_SDK/QEnvPython/python38/Lib/site-packages/pip/_internal/__init__.py
QPT_SDK/QEnvPython/python38/Lib/site-packages/setuptools-68.2.2.dist-info/INSTALLER
QPT_SDK/QEnvPython/python38/Lib/site-packages/setuptools-68.2.2.dist-info/LICENSE
QPT_SDK/QEnvPython/python38/Lib/site-packages/setuptools-68.2.2.dist-info/METADATA
QPT_SDK/QEnvPython/python38/Lib/site-packages/setuptools-68.2.2.dist-info/RECORD
QPT_SDK/QEnvPython/python38/Lib/site-packages/setuptools-68.2.2.dist-info/REQUESTED
QPT_SDK/QEnvPython/python38/Lib/site-packages/setuptools-68.2.2.dist-info/WHEEL
QPT_SDK/QEnvPython/python38/Lib/site-packages/setuptools-68.2.2.dist-info/entry_points.txt
QPT_SDK/QEnvPython/python38/Lib/site-packages/setuptools-68.2.2.dist-info/top_level.txt
QPT_SDK/QEnvPython/python38/Lib/site-packages/wheel-0.41.2.dist-info/INSTALLER
QPT_SDK/QEnvPython/python38/Lib/site-packages/wheel-0.41.2.dist-info/LICENSE.txt
QPT_SDK/QEnvPython/python38/Lib/site-packages/wheel-0.41.2.dist-info/METADATA
QPT_SDK/QEnvPython/python38/Lib/site-packages/wheel-0.41.2.dist-info/RECORD
QPT_SDK/QEnvPython/python38/Lib/site-packages/wheel-0.41.2.dist-info/REQUESTED
QPT_SDK/QEnvPython/python38/Lib/site-packages/wheel-0.41.2.dist-info/WHEEL
QPT_SDK/QEnvPython/python38/Lib/site-packages/wheel-0.41.2.dist-info/entry_points.txt
